Workbook

Sheet Weekly
A1: Week ending | B1: Price | C1: Surcharge | D1: Gallons | E1: Fleet fuel cost | F1: Fuel cost per mile | G1: Source | I1: Prices (column B) are values from weekly_prices.csv; all other columns are formulas. API URL: https://api.eia.gov/v2/petroleum/pri/gnd/data/?frequency=weekly&data[0]=value&facets[series][]=EMD_EPD2D_PTE_R20_DPG&sort[0][column]=period&sort[0][direction]=desc&length=52 (api_key=DEMO_KEY)
A2: 45957 | B2: 3.715 | C2: =ROUND((B2-Inputs!$B$4)/Inputs!$B$5,2) -> 0.4 | D2: =Inputs!$B$9 -> 12983.871 | E2: =B2*D2 -> 48235.081 | F2: =B2/Inputs!$B$5 -> 0.59919355 | G2: EIA series EMD_EPD2D_PTE_R20_DPG (Midwest PADD 2 weekly retail diesel), retrieved 2026-10-23
A3: 45964 | B3: 3.773 | C3: =ROUND((B3-Inputs!$B$4)/Inputs!$B$5,2) -> 0.41 | D3: =Inputs!$B$9 -> 12983.871 | E3: =B3*D3 -> 48988.145 | F3: =B3/Inputs!$B$5 -> 0.60854839 | G3: EIA series EMD_EPD2D_PTE_R20_DPG (Midwest PADD 2 weekly retail diesel), retrieved 2026-10-23
A4: 45971 | B4: 3.891 | C4: =ROUND((B4-Inputs!$B$4)/Inputs!$B$5,2) -> 0.43 | D4: =Inputs!$B$9 -> 12983.871 | E4: =B4*D4 -> 50520.242 | F4: =B4/Inputs!$B$5 -> 0.62758065 | G4: EIA series EMD_EPD2D_PTE_R20_DPG (Midwest PADD 2 weekly retail diesel), retrieved 2026-10-23
A5: 45978 | B5: 3.913 | C5: =ROUND((B5-Inputs!$B$4)/Inputs!$B$5,2) -> 0.43 | D5: =Inputs!$B$9 -> 12983.871 | E5: =B5*D5 -> 50805.887 | F5: =B5/Inputs!$B$5 -> 0.63112903 | G5: EIA series EMD_EPD2D_PTE_R20_DPG (Midwest PADD 2 weekly retail diesel), retrieved 2026-10-23
A6: 45985 | B6: 3.85 | C6: =ROUND((B6-Inputs!$B$4)/Inputs!$B$5,2) -> 0.42 | D6: =Inputs!$B$9 -> 12983.871 | E6: =B6*D6 -> 49987.903 | F6: =B6/Inputs!$B$5 -> 0.62096774 | G6: EIA series EMD_EPD2D_PTE_R20_DPG (Midwest PADD 2 weekly retail diesel), retrieved 2026-10-23
A7: 45992 | B7: 3.755 | C7: =ROUND((B7-Inputs!$B$4)/Inputs!$B$5,2) -> 0.4 | D7: =Inputs!$B$9 -> 12983.871 | E7: =B7*D7 -> 48754.435 | F7: =B7/Inputs!$B$5 -> 0.60564516 | G7: EIA series EMD_EPD2D_PTE_R20_DPG (Midwest PADD 2 weekly retail diesel), retrieved 2026-10-23
A8: 45999 | B8: 3.635 | C8: =ROUND((B8-Inputs!$B$4)/Inputs!$B$5,2) -> 0.38 | D8: =Inputs!$B$9 -> 12983.871 | E8: =B8*D8 -> 47196.371 | F8: =B8/Inputs!$B$5 -> 0.58629032 | G8: EIA series EMD_EPD2D_PTE_R20_DPG (Midwest PADD 2 weekly retail diesel), retrieved 2026-10-23
A9: 46006 | B9: 3.567 | C9: =ROUND((B9-Inputs!$B$4)/Inputs!$B$5,2) -> 0.37 | D9: =Inputs!$B$9 -> 12983.871 | E9: =B9*D9 -> 46313.468 | F9: =B9/Inputs!$B$5 -> 0.57532258 | G9: EIA series EMD_EPD2D_PTE_R20_DPG (Midwest PADD 2 weekly retail diesel), retrieved 2026-10-23
A10: 46013 | B10: 3.483 | C10: =ROUND((B10-Inputs!$B$4)/Inputs!$B$5,2) -> 0.36 | D10: =Inputs!$B$9 -> 12983.871 | E10: =B10*D10 -> 45222.823 | F10: =B10/Inputs!$B$5 -> 0.56177419 | G10: EIA series EMD_EPD2D_PTE_R20_DPG (Midwest PADD 2 weekly retail diesel), retrieved 2026-10-23
A11: 46020 | B11: 3.424 | C11: =ROUND((B11-Inputs!$B$4)/Inputs!$B$5,2) -> 0.35 | D11: =Inputs!$B$9 -> 12983.871 | E11: =B11*D11 -> 44456.774 | F11: =B11/Inputs!$B$5 -> 0.55225806 | G11: EIA series EMD_EPD2D_PTE_R20_DPG (Midwest PADD 2 weekly retail diesel), retrieved 2026-10-23
A12: 46027 | B12: 3.387 | C12: =ROUND((B12-Inputs!$B$4)/Inputs!$B$5,2) -> 0.34 | D12: =Inputs!$B$9 -> 12983.871 | E12: =B12*D12 -> 43976.371 | F12: =B12/Inputs!$B$5 -> 0.54629032 | G12: EIA series EMD_EPD2D_PTE_R20_DPG (Midwest PADD 2 weekly retail diesel), retrieved 2026-10-23
A13: 46034 | B13: 3.365 | C13: =ROUND((B13-Inputs!$B$4)/Inputs!$B$5,2) -> 0.34 | D13: =Inputs!$B$9 -> 12983.871 | E13: =B13*D13 -> 43690.726 | F13: =B13/Inputs!$B$5 -> 0.54274194 | G13: EIA series EMD_EPD2D_PTE_R20_DPG (Midwest PADD 2 weekly retail diesel), retrieved 2026-10-23
... A53: 46314 | B53: 6.352 | C53: =ROUND((B53-Inputs!$B$4)/Inputs!$B$5,2) -> 0.82 | D53: =Inputs!$B$9 -> 12983.871 | E53: =B53*D53 -> 82473.548 | F53: =B53/Inputs!$B$5 -> 1.0245161 | G53: EIA series EMD_EPD2D_PTE_R20_DPG (Midwest PADD 2 weekly retail diesel), retrieved 2026-10-23

Sheet Inputs
A1: Fleet fuel surcharge model - Inputs
A2: Yellow cells are the only hard-coded parameters; edit them and every sheet recalculates.
A3: Parameter | B3: Value | C3: Basis
A4: Base price ($/gal) | B4: 1.25 | C4: Standard base price in the task
A5: Fleet fuel economy (mpg) | B5: 6.2 | C5: Given in the task: Class 8 tractors average 6.2 mpg
A6: Tractors (count) | B6: 35 | C6: Given in the task
A7: Miles per tractor per week | B7: 2300 | C7: Given in the task
A8: Fleet miles per week (derived) | B8: =B6*B7 -> 80500 | C8: Tractors x miles per tractor
A9: Fleet gallons per week (derived) | B9: =B8/B5 -> 12983.871 | C9: Fleet miles divided by mpg
A11: Assumption notes
A12: 1. Constant gallons: every week uses the same gallons (35 x 2,300 / 6.2); miles and mpg do not vary by week.
A13: 2. Midpoint band convention: each 5-cent band surcharge is computed at the band midpoint, ROUND((midpoint - base)/mpg, 2).
A14: 3. Surcharge applies to every mile, loaded and empty: Surcharge per mile = ROUND((price - base) / mpg, 2).
A15: 4. Class 8 = heavy-duty truck with GVWR over 33,000 lb (semi tractor).
A16: 5. Price proxy: EIA weekly Midwest (PADD 2) No. 2 diesel retail price (series EMD_EPD2D_PTE_R20_DPG); EIA publishes no Indiana-only weekly series.
A17: 6. Fleet fuel cost = price x weekly gallons; fuel cost per mile = price / mpg (no tax or discount adjustments).
A18: 7. Band grid (start $3.00, 5-cent step) is on the Bands sheet as labelled grid settings from the task, not a carrier parameter.

Sheet Bands
A1: Band | B1: Low $/gal | C1: High $/gal | D1: Midpoint $/gal | E1: Surcharge $/mi | G1: Band grid start ($/gal) | H1: 3
A2: 1 | B2: =$H$1 -> 3 | C2: =ROUND(B2+$H$2,2) -> 3.05 | D2: =ROUND((B2+C2)/2,3) -> 3.025 | E2: =ROUND((D2-Inputs!$B$4)/Inputs!$B$5,2) -> 0.29 | G2: Band width ($/gal) | H2: 0.05
A3: 2 | B3: =C2 -> 3.05 | C3: =ROUND(B3+$H$2,2) -> 3.1 | D3: =ROUND((B3+C3)/2,3) -> 3.075 | E3: =ROUND((D3-Inputs!$B$4)/Inputs!$B$5,2) -> 0.29 | G3: Grid settings from the task ($3.00 to $5.00, 5-cent bands); surcharge at midpoint.
A4: 3 | B4: =C3 -> 3.1 | C4: =ROUND(B4+$H$2,2) -> 3.15 | D4: =ROUND((B4+C4)/2,3) -> 3.125 | E4: =ROUND((D4-Inputs!$B$4)/Inputs!$B$5,2) -> 0.3
A5: 4 | B5: =C4 -> 3.15 | C5: =ROUND(B5+$H$2,2) -> 3.2 | D5: =ROUND((B5+C5)/2,3) -> 3.175 | E5: =ROUND((D5-Inputs!$B$4)/Inputs!$B$5,2) -> 0.31
A6: 5 | B6: =C5 -> 3.2 | C6: =ROUND(B6+$H$2,2) -> 3.25 | D6: =ROUND((B6+C6)/2,3) -> 3.225 | E6: =ROUND((D6-Inputs!$B$4)/Inputs!$B$5,2) -> 0.32
A7: 6 | B7: =C6 -> 3.25 | C7: =ROUND(B7+$H$2,2) -> 3.3 | D7: =ROUND((B7+C7)/2,3) -> 3.275 | E7: =ROUND((D7-Inputs!$B$4)/Inputs!$B$5,2) -> 0.33
A8: 7 | B8: =C7 -> 3.3 | C8: =ROUND(B8+$H$2,2) -> 3.35 | D8: =ROUND((B8+C8)/2,3) -> 3.325 | E8: =ROUND((D8-Inputs!$B$4)/Inputs!$B$5,2) -> 0.33
A9: 8 | B9: =C8 -> 3.35 | C9: =ROUND(B9+$H$2,2) -> 3.4 | D9: =ROUND((B9+C9)/2,3) -> 3.375 | E9: =ROUND((D9-Inputs!$B$4)/Inputs!$B$5,2) -> 0.34
A10: 9 | B10: =C9 -> 3.4 | C10: =ROUND(B10+$H$2,2) -> 3.45 | D10: =ROUND((B10+C10)/2,3) -> 3.425 | E10: =ROUND((D10-Inputs!$B$4)/Inputs!$B$5,2) -> 0.35
A11: 10 | B11: =C10 -> 3.45 | C11: =ROUND(B11+$H$2,2) -> 3.5 | D11: =ROUND((B11+C11)/2,3) -> 3.475 | E11: =ROUND((D11-Inputs!$B$4)/Inputs!$B$5,2) -> 0.36
A12: 11 | B12: =C11 -> 3.5 | C12: =ROUND(B12+$H$2,2) -> 3.55 | D12: =ROUND((B12+C12)/2,3) -> 3.525 | E12: =ROUND((D12-Inputs!$B$4)/Inputs!$B$5,2) -> 0.37
A13: 12 | B13: =C12 -> 3.55 | C13: =ROUND(B13+$H$2,2) -> 3.6 | D13: =ROUND((B13+C13)/2,3) -> 3.575 | E13: =ROUND((D13-Inputs!$B$4)/Inputs!$B$5,2) -> 0.38
A14: 13 | B14: =C13 -> 3.6 | C14: =ROUND(B14+$H$2,2) -> 3.65 | D14: =ROUND((B14+C14)/2,3) -> 3.625 | E14: =ROUND((D14-Inputs!$B$4)/Inputs!$B$5,2) -> 0.38
A15: 14 | B15: =C14 -> 3.65 | C15: =ROUND(B15+$H$2,2) -> 3.7 | D15: =ROUND((B15+C15)/2,3) -> 3.675 | E15: =ROUND((D15-Inputs!$B$4)/Inputs!$B$5,2) -> 0.39
... A41: 40 | B41: =C40 -> 4.95 | C41: =ROUND(B41+$H$2,2) -> 5 | D41: =ROUND((B41+C41)/2,3) -> 4.975 | E41: =ROUND((D41-Inputs!$B$4)/Inputs!$B$5,2) -> 0.6

Sheet Summary
A1: Summary - 52 weeks, EIA Midwest (PADD 2) weekly retail diesel, proxy for Indiana
A3: Metric | B3: Value | C3: Formula / source | D3: As of
A4: Average price ($/gal) | B4: =AVERAGE(Weekly!$B$2:$B$53) -> 4.7873846 | C4: AVERAGE(Weekly!B2:B53); EIA EMD_EPD2D_PTE_R20_DPG | D4: Weeks ending 2025-10-27 to 2026-10-19
A5: Average surcharge ($/mi) | B5: =AVERAGE(Weekly!$C$2:$C$53) -> 0.57076923 | C5: AVERAGE(Weekly!C2:C53) | D5: same 52 weeks
A6: Highest price ($/gal) | B6: =MAX(Weekly!$B$2:$B$53) -> 6.68 | C6: MAX(Weekly!B2:B53) | D6: same 52 weeks
A7: Highest week (week ending) | B7: =INDEX(Weekly!$A$2:$A$53,MATCH(B6,Weekly!$B$2:$B$53,0)) -> 46286 | C7: INDEX/MATCH on highest price (first match if tied) | D7: same 52 weeks
A8: Surcharge in highest week ($/mi) | B8: =INDEX(Weekly!$C$2:$C$53,MATCH(B6,Weekly!$B$2:$B$53,0)) -> 0.88 | C8: INDEX/MATCH | D8: same 52 weeks
A9: Lowest price ($/gal) | B9: =MIN(Weekly!$B$2:$B$53) -> 3.365 | C9: MIN(Weekly!B2:B53) | D9: same 52 weeks
A10: Lowest week (week ending) | B10: =INDEX(Weekly!$A$2:$A$53,MATCH(B9,Weekly!$B$2:$B$53,0)) -> 46034 | C10: INDEX/MATCH on lowest price (first match if tied) | D10: same 52 weeks
A11: Surcharge in lowest week ($/mi) | B11: =INDEX(Weekly!$C$2:$C$53,MATCH(B9,Weekly!$B$2:$B$53,0)) -> 0.34 | C11: INDEX/MATCH | D11: same 52 weeks
A12: 52-week total fleet fuel cost ($) | B12: =SUM(Weekly!$E$2:$E$53) -> 3232256.8 | C12: SUM(Weekly!E2:E53) | D12: same 52 weeks
A13: Average weekly fleet fuel cost ($) | B13: =AVERAGE(Weekly!$E$2:$E$53) -> 62158.784 | C13: AVERAGE(Weekly!E2:E53) | D13: same 52 weeks
A14: Carrier average fuel cost per mile ($/mi) | B14: =AVERAGE(Weekly!$F$2:$F$53) -> 0.77215881 | C14: AVERAGE(Weekly!F2:F53); weekly price / 6.2 mpg | D14: same 52 weeks
A15: ATRI total marginal cost per mile ($/mi) - INPUT | B15: =Sources!B21 -> 2.336 | C15: ATRI, An Analysis of the Operational Costs of Trucking (2026 ed.), press release https://truckingresearch.org/2026/07/new-atri-report-details-accelerating-costs-and-low-profitability-despite-cuts [S35][S46] | D15: Cost data year 2025; released 2026-07-15; retrieved 2026-10-23
A16: ATRI cost per mile excluding fuel ($/mi) - INPUT | B16: =Sources!B22 -> 1.854 | C16: Same ATRI report and page [S46] | D16: Cost data year 2025; released 2026-07-15; retrieved 2026-10-23
A17: ATRI fuel cost per mile ($/mi) - SUBSTITUTE | B17: =B15-B16 -> 0.482 | C17: SUBSTITUTE: stated fuel $/mi table value NOT FOUND; derived as total minus non-fuel (2.336 - 1.854 = 0.482) | D17: Cost data year 2025; released 2026-07-15
A18: ATRI fuel share of total marginal cost | B18: =B17/B15 -> 0.20633562 | C18: Derived: ATRI fuel $/mi / ATRI total $/mi (uses the substitute above) | D18: Cost data year 2025; released 2026-07-15
A19: Gap: carrier minus ATRI fuel per mile ($/mi) | B19: =B14-B17 -> 0.29015881 | C19: Carrier 52-week average (B14) minus ATRI fuel $/mi (B17) | D19: Carrier: 2025-10-27 to 2026-10-19; ATRI: 2025 data
A20: Gap as % of ATRI fuel per mile | B20: =B19/B17 -> 0.60198923 | C20: B19 / B17 | D20: as above
A22: Legend: yellow cells on Sources (B21, B22) hold the typed ATRI inputs with source and date; Summary B15 and B16 are formulas pointing to them. Orange = substitute (derived, not a stated table figure). Carrier $/mi is 2025-26 price / 6.2 mpg; ATRI is a 2025 industry sample average, so year and basis differ.

Sheet Sources
A1: Sources
A3: Item | B3: Detail | C3: Retrieved / as of
A4: Proxy statement | B4: EIA publishes no Indiana-only weekly retail diesel series; the EIA weekly Midwest (PADD 2) retail diesel price is used as a proxy for Indiana (an assumption). | C4: Applied 2026-10-23
A5: EIA series ID | B5: EMD_EPD2D_PTE_R20_DPG - Weekly Midwest No. 2 Diesel Retail Prices, dollars per gallon [S1] | C5: Retrieved 2026-10-23
A6: EIA page URL | B6: https://www.eia.gov/dnav/pet/hist/LeafHandler.ashx?n=PET&s=emd_epd2d_pte_r20_dpg&f=W [S1] | C6: Retrieved 2026-10-23
A7: EIA API URL | B7: EIA API v2 petroleum/pri/gnd data route (URL in Weekly!I1) [S64] | C7: Retrieved 2026-10-23
A8: Price period | B8: 52 weeks, weeks ending 2025-10-27 to 2026-10-19; latest week as of 2026-10-19 = 6.352 $/gal (FRED shows the same value [S58]) | C8: Retrieved 2026-10-23
A9: ATRI report title | B9: An Analysis of the Operational Costs of Trucking, 2026 edition (press headline: New ATRI Report Details Accelerating Costs and Low Profitability Despite Cuts) | C9: Retrieved 2026-10-23
A10: ATRI URL | B10: https://truckingresearch.org/2026/07/new-atri-report-details-accelerating-costs-and-low-profitability-despite-cuts [S35][S46] | C10: Retrieved 2026-10-23
A11: ATRI release date | B11: 2026-07-15 (page dateline "Wednesday, July 15, 2026" [S47]; press release says "today released") | C11: as of 2026-07-15
A12: ATRI cost data year | B12: 2025; sample 182,248 trucks and 14.67 billion miles [S46] | C12: Data year 2025
A13: ATRI figures used | B13: Total marginal cost 2.336 $/mi (+3.4%); cost excluding fuel 1.854 $/mi (+4.2%) [S46] | C13: as of 2026-07-15 release
A14: ATRI SUBSTITUTE (marked) | B14: Fuel cost per mile stated as a table value NOT FOUND (press release and summary page only; full PDF not read). Substitute: 2.336 - 1.854 = 0.482 $/mi; share 0.482/2.336 = 20.6%. | C14: Derived 2026-10-23
... A18: Surcharge method | B18: ROUND((price - 1.25) / 6.2, 2), every loaded and empty mile | C18: Task
A20: ATRI input cells (typed values, referenced by Summary!B15 and B16)
A21: ATRI total marginal cost per mile ($/mi), cost data year 2025 | B21: 2.336 | C21: Source: ATRI 2026 edition press release [S46]; released 2026-07-15; retrieved 2026-10-23
A22: ATRI cost per mile excluding fuel ($/mi), cost data year 2025 | B22: 1.854 | C22: Source: ATRI 2026 edition press release [S46]; released 2026-07-15; retrieved 2026-10-23
